README.md
setup.py
unwrap_labels.py
unwrap_labels.egg-info/PKG-INFO
unwrap_labels.egg-info/SOURCES.txt
unwrap_labels.egg-info/dependency_links.txt
unwrap_labels.egg-info/requires.txt
unwrap_labels.egg-info/top_level.txt