Metadata-Version: 1.1
Name: unwrap-labels
Version: 1.0.8
Summary: Library to unwrap labels using OpenCV
Home-page: https://github.com/Nepherhotep/unwrap_labels
Author: Alexey Zankevich
Author-email: alex.zankevich@gmail.com
License: MIT
Keywords: OpenCV
Platform: Platform Independent
Classifier: Development Status :: 5 - Production/Stable
Classifier: Programming Language :: Python :: 2.7
Classifier: Programming Language :: Python :: 3.5
Classifier: Programming Language :: Python :: 3.6
Classifier: Programming Language :: Python :: 3.7
